[{"name": "\uc11c\uc6b8\ubca0\uc2a4\ud2b8\uc548\uacfc\uc758\uc6d0", "lat": "37.5794848121", "lng": "127.0421004343", "url": "/info/%EC%84%9C%EC%9A%B8%EB%B2%A0%EC%8A%A4%ED%8A%B8%EC%95%88%EA%B3%BC%EC%9D%98%EC%9B%90-%EC%84%9C%EC%9A%B8%ED%8A%B9%EB%B3%84%EC%8B%9C-%EB%8F%99%EB%8C%80%EB%AC%B8%EA%B5%AC-%EC%A0%9C%EA%B8%B0%EB%8F%99/", "workingTime": ["-", "09:00~18:30", "09:00~18:30", "09:00~18:30", "09:00~18:30", "09:00~18:30", "09:00~14:00", "-"], "course": ["\uc548\uacfc"]}, {"name": "\uc131\ucc3d\ud55c\uc758\uc6d0", "lat": "37.5789636247", "lng": "127.0380065057", "url": "/info/%EC%84%B1%EC%B0%BD%ED%95%9C%EC%9D%98%EC%9B%90-%EC%84%9C%EC%9A%B8%ED%8A%B9%EB%B3%84%EC%8B%9C-%EB%8F%99%EB%8C%80%EB%AC%B8%EA%B5%AC-%EC%A0%9C%EA%B8%B0%EB%8F%99/", "workingTime": ["-", "10:00~18:00", "10:00~18:00", "10:00~18:00", "10:00~18:00", "10:00~18:00", "10:00~16:00", "10:00~17:30"], "course": ["\ud55c\ubc29\ub0b4\uacfc"]}, {"name": "\uc81c\uc778\ud55c\uc758\uc6d0", "lat": "37.57888457688184", "lng": "127.037254758974", "url": "/info/%EC%A0%9C%EC%9D%B8%ED%95%9C%EC%9D%98%EC%9B%90-%EC%84%9C%EC%9A%B8%ED%8A%B9%EB%B3%84%EC%8B%9C-%EB%8F%99%EB%8C%80%EB%AC%B8%EA%B5%AC-%EC%A0%9C%EA%B8%B0%EB%8F%99/", "workingTime": ["-", "09:30~19:00", "-", "09:30~19:00", "09:30~19:00", "09:30~19:00", "09:30~17:00", "-"], "course": ["\uc0ac\uc0c1\uccb4\uc9c8\uacfc", "\uce68\uad6c\uacfc", "\ud55c\ubc29\ub0b4\uacfc", "\ud55c\ubc29\ubd80\uc778\uacfc", "\ud55c\ubc29\uc18c\uc544\uacfc", "\ud55c\ubc29\uc2e0\uacbd\uc815\uc2e0\uacfc", "\ud55c\ubc29\uc548\uc774\ube44\uc778\ud6c4\ud53c\ubd80\uacfc", "\ud55c\ubc29\uc7ac\ud65c\uc758\ud559\uacfc"]}, {"name": "\uc21c\ud658\ud55c\uc758\uc6d0", "lat": "37.5784958557261", "lng": "127.036492900333", "url": "/info/%EC%88%9C%ED%99%98%ED%95%9C%EC%9D%98%EC%9B%90-%EC%84%9C%EC%9A%B8%ED%8A%B9%EB%B3%84%EC%8B%9C-%EB%8F%99%EB%8C%80%EB%AC%B8%EA%B5%AC-%EC%A0%9C%EA%B8%B0%EB%8F%99/", "workingTime": ["1,2,3,4,5\uc9f8\uc8fc09:00~13:00", "09:00~18:00", "09:00~18:00", "09:00~18:00", "09:00~18:00", "09:00~18:00", "09:00~13:00", "09:00~13:00"], "course": ["\uc0ac\uc0c1\uccb4\uc9c8\uacfc", "\uce68\uad6c\uacfc", "\ud55c\ubc29\ub0b4\uacfc", "\ud55c\ubc29\ubd80\uc778\uacfc", "\ud55c\ubc29\uc18c\uc544\uacfc", "\ud55c\ubc29\uc2e0\uacbd\uc815\uc2e0\uacfc", "\ud55c\ubc29\uc548\uc774\ube44\uc778\ud6c4\ud53c\ubd80\uacfc", "\ud55c\ubc29\uc751\uae09\uacfc", "\ud55c\ubc29\uc7ac\ud65c\uc758\ud559\uacfc"]}, {"name": "\uc704\ud48d\ub2f9\ub2f9\uc2e0\uacbd\uc678\uacfc\uc758\uc6d0", "lat": "37.579416482853404", "lng": "127.04168831279182", "url": "/info/%EC%9C%84%ED%92%8D%EB%8B%B9%EB%8B%B9%EC%8B%A0%EA%B2%BD%EC%99%B8%EA%B3%BC%EC%9D%98%EC%9B%90-%EC%84%9C%EC%9A%B8%ED%8A%B9%EB%B3%84%EC%8B%9C-%EB%8F%99%EB%8C%80%EB%AC%B8%EA%B5%AC-%EC%A0%9C%EA%B8%B0%EB%8F%99/", "workingTime": ["-", "09:00~19:00", "09:00~19:00", "09:00~19:00", "09:00~19:00", "09:00~19:00", "09:00~14:00", "-"], "course": ["\ub0b4\uacfc", "\ub9c8\ucde8\ud1b5\uc99d\uc758\ud559\uacfc", "\uc2e0\uacbd\uc678\uacfc", "\uc7ac\ud65c\uc758\ud559\uacfc", "\uc815\ud615\uc678\uacfc"]}, {"name": "\uc544\ub9ac\ub791\ud55c\uc758\uc6d0", "lat": "37.5784484055", "lng": "127.0375398262", "url": "/info/%EC%95%84%EB%A6%AC%EB%9E%91%ED%95%9C%EC%9D%98%EC%9B%90-%EC%84%9C%EC%9A%B8%ED%8A%B9%EB%B3%84%EC%8B%9C-%EB%8F%99%EB%8C%80%EB%AC%B8%EA%B5%AC-%EC%A0%9C%EA%B8%B0%EB%8F%99/", "workingTime": ["-", "09:00~17:00", "09:00~21:00", "09:00~17:00", "09:00~21:00", "09:00~17:00", "09:00~14:00", "09:00~14:00"], "course": ["\uc0ac\uc0c1\uccb4\uc9c8\uacfc", "\uce68\uad6c\uacfc", "\ud55c\ubc29\ub0b4\uacfc", "\ud55c\ubc29\ubd80\uc778\uacfc", "\ud55c\ubc29\uc18c\uc544\uacfc", "\ud55c\ubc29\uc2e0\uacbd\uc815\uc2e0\uacfc", "\ud55c\ubc29\uc548\uc774\ube44\uc778\ud6c4\ud53c\ubd80\uacfc", "\ud55c\ubc29\uc7ac\ud65c\uc758\ud559\uacfc"]}, {"name": "\uc11c\uc6b8\ud0d1\ubcd1\uc6d0", "lat": "37.58142576137001", "lng": "127.03602427138746", "url": "/info/%EC%84%9C%EC%9A%B8%ED%83%91%EB%B3%91%EC%9B%90-%EC%84%9C%EC%9A%B8%ED%8A%B9%EB%B3%84%EC%8B%9C-%EB%8F%99%EB%8C%80%EB%AC%B8%EA%B5%AC-%EC%A0%9C%EA%B8%B0%EB%8F%99/", "workingTime": ["-", "08:30~17:30", "08:30~17:30", "08:30~17:30", "08:30~17:30", "08:30~17:30", "-", "-"], "course": ["\uac00\uc815\uc758\ud559\uacfc", "\ub0b4\uacfc", "\uc2e0\uacbd\uacfc", "\uc2e0\uacbd\uc678\uacfc", "\uc601\uc0c1\uc758\ud559\uacfc", "\uc7ac\ud65c\uc758\ud559\uacfc", "\uc815\ud615\uc678\uacfc", "\uce68\uad6c\uacfc", "\ud55c\ubc29\ub0b4\uacfc", "\ud55c\ubc29\uc7ac\ud65c\uc758\ud559\uacfc"]}, {"name": "\uc81c\uae30\ub3d9\uc815\ud615\uc678\uacfc\uc758\uc6d0", "lat": "37.5784272619867", "lng": "127.037160568378", "url": "/info/%EC%A0%9C%EA%B8%B0%EB%8F%99%EC%A0%95%ED%98%95%EC%99%B8%EA%B3%BC%EC%9D%98%EC%9B%90-%EC%84%9C%EC%9A%B8%ED%8A%B9%EB%B3%84%EC%8B%9C-%EB%8F%99%EB%8C%80%EB%AC%B8%EA%B5%AC-%EC%A0%9C%EA%B8%B0%EB%8F%99/", "workingTime": ["-", "08:30~18:30", "08:30~18:30", "08:30~18:30", "08:30~18:30", "08:30~18:30", "08:30~13:00", "-"], "course": ["\ub0b4\uacfc", "\ub9c8\ucde8\ud1b5\uc99d\uc758\ud559\uacfc", "\uc2e0\uacbd\uacfc", "\uc2e0\uacbd\uc678\uacfc", "\uc678\uacfc", "\uc7ac\ud65c\uc758\ud559\uacfc", "\uc815\ud615\uc678\uacfc"]}, {"name": "\uc608\uc9c4\uc0b0\ubd80\uc778\uacfc\uc758\uc6d0", "lat": "37.579769212543454", "lng": "127.04296101230255", "url": "/info/%EC%98%88%EC%A7%84%EC%82%B0%EB%B6%80%EC%9D%B8%EA%B3%BC%EC%9D%98%EC%9B%90-%EC%84%9C%EC%9A%B8%ED%8A%B9%EB%B3%84%EC%8B%9C-%EB%8F%99%EB%8C%80%EB%AC%B8%EA%B5%AC-%EC%A0%9C%EA%B8%B0%EB%8F%99/", "workingTime": ["-", "09:30~18:00", "09:30~18:00", "-", "09:30~18:00", "09:30~18:00", "09:30~13:00", "-"], "course": ["\uac00\uc815\uc758\ud559\uacfc", "\uc0b0\ubd80\uc778\uacfc", "\ud53c\ubd80\uacfc"]}, {"name": "\ub3d9\ud638\uad8c\uac00\uc815\uc758\ud559\uacfc\uc758\uc6d0", "lat": "37.58752426047808", "lng": "127.03808293103506", "url": "/info/%EB%8F%99%ED%98%B8%EA%B6%8C%EA%B0%80%EC%A0%95%EC%9D%98%ED%95%99%EA%B3%BC%EC%9D%98%EC%9B%90-%EC%84%9C%EC%9A%B8%ED%8A%B9%EB%B3%84%EC%8B%9C-%EB%8F%99%EB%8C%80%EB%AC%B8%EA%B5%AC-%EC%A0%9C%EA%B8%B0%EB%8F%99/", "workingTime": ["-", "09:00~18:00", "09:00~18:00", "09:00~18:00", "09:00~18:00", "09:00~18:00", "-", "-"], "course": ["\uac00\uc815\uc758\ud559\uacfc"]}, {"name": "\ud5c8\uce58\uacfc\uc758\uc6d0", "lat": "37.587509839101784", "lng": "127.03810103933529", "url": "/info/%ED%97%88%EC%B9%98%EA%B3%BC%EC%9D%98%EC%9B%90-%EC%84%9C%EC%9A%B8%ED%8A%B9%EB%B3%84%EC%8B%9C-%EB%8F%99%EB%8C%80%EB%AC%B8%EA%B5%AC-%EC%A0%9C%EA%B8%B0%EB%8F%99/", "workingTime": ["-", "09:30~18:00", "09:30~18:00", "09:30~18:00", "14:00~18:00", "09:30~18:00", "09:30~13:00", "-"], "course": ["\uce58\uacfc"]}, {"name": "\uc6b0\ub9ac\uce58\uacfc\uc758\uc6d0", "lat": "37.582138421605", "lng": "127.03893196443485", "url": "/info/%EC%9A%B0%EB%A6%AC%EC%B9%98%EA%B3%BC%EC%9D%98%EC%9B%90-%EC%84%9C%EC%9A%B8%ED%8A%B9%EB%B3%84%EC%8B%9C-%EB%8F%99%EB%8C%80%EB%AC%B8%EA%B5%AC-%EC%A0%9C%EA%B8%B0%EB%8F%99/", "workingTime": ["-", "09:30~18:00", "09:30~18:00", "09:30~18:00", "09:30~18:00", "09:30~18:00", "-", "-"], "course": ["\uce58\uacfc"]}, {"name": "\uc62c\ub9ac\ube0c\uce58\uacfc\uc758\uc6d0", "lat": "37.5896714303", "lng": "127.0367347702", "url": "/info/%EC%98%AC%EB%A6%AC%EB%B8%8C%EC%B9%98%EA%B3%BC%EC%9D%98%EC%9B%90-%EC%84%9C%EC%9A%B8%ED%8A%B9%EB%B3%84%EC%8B%9C-%EB%8F%99%EB%8C%80%EB%AC%B8%EA%B5%AC-%EC%A0%9C%EA%B8%B0%EB%8F%99/", "workingTime": ["-", "09:30~18:00", "09:30~18:00", "09:30~18:00", "09:30~18:00", "09:30~18:00", "09:00~13:00", "-"], "course": ["\uad6c\uac15\ub0b4\uacfc", "\uad6c\uac15\ubcd1\ub9ac\uacfc", "\uad6c\uac15\uc545\uc548\uba74\ubc29\uc0ac\uc120\uacfc", "\uc18c\uc544\uce58\uacfc", "\uc608\ubc29\uce58\uacfc", "\uce58\uacfc\uad50\uc815\uacfc", "\uce58\uacfc\ubcf4\uc874\uacfc", "\uce58\uacfc\ubcf4\ucca0\uacfc", "\uce58\uc8fc\uacfc"]}, {"name": "\uacbd\ud76c\ub300\uc6b4\ud55c\uc758\uc6d0", "lat": "37.5789620035398", "lng": "127.038004580324", "url": "/info/%EA%B2%BD%ED%9D%AC%EB%8C%80%EC%9A%B4%ED%95%9C%EC%9D%98%EC%9B%90-%EC%84%9C%EC%9A%B8%ED%8A%B9%EB%B3%84%EC%8B%9C-%EB%8F%99%EB%8C%80%EB%AC%B8%EA%B5%AC-%EC%A0%9C%EA%B8%B0%EB%8F%99/", "workingTime": ["-", "10:00~17:00", "10:00~17:00", "10:00~17:00", "10:00~17:00", "10:00~17:00", "10:00~15:00", "10:00~15:00"], "course": ["\uc0ac\uc0c1\uccb4\uc9c8\uacfc", "\uce68\uad6c\uacfc", "\ud55c\ubc29\ub0b4\uacfc", "\ud55c\ubc29\ubd80\uc778\uacfc", "\ud55c\ubc29\uc18c\uc544\uacfc", "\ud55c\ubc29\uc2e0\uacbd\uc815\uc2e0\uacfc", "\ud55c\ubc29\uc548\uc774\ube44\uc778\ud6c4\ud53c\ubd80\uacfc", "\ud55c\ubc29\uc7ac\ud65c\uc758\ud559\uacfc"]}, {"name": "\uc608\ub2f4\uce58\uacfc\uc758\uc6d0", "lat": "37.5828020608309", "lng": "127.030122143894", "url": "/info/%EC%98%88%EB%8B%B4%EC%B9%98%EA%B3%BC%EC%9D%98%EC%9B%90-%EC%84%9C%EC%9A%B8%ED%8A%B9%EB%B3%84%EC%8B%9C-%EB%8F%99%EB%8C%80%EB%AC%B8%EA%B5%AC-%EC%A0%9C%EA%B8%B0%EB%8F%99/", "workingTime": ["-", "09:30~18:30", "09:30~18:30", "09:30~20:30", "09:30~18:30", "09:30~18:30", "09:30~14:00", "-"], "course": ["\uce58\uacfc"]}, {"name": "\uc5f0\uc138\uc138\ube0c\ub780\uc2a4\uce58\uacfc\uc758\uc6d0", "lat": "37.5788570401089", "lng": "127.040174173148", "url": "/info/%EC%97%B0%EC%84%B8%EC%84%B8%EB%B8%8C%EB%9E%80%EC%8A%A4%EC%B9%98%EA%B3%BC%EC%9D%98%EC%9B%90-%EC%84%9C%EC%9A%B8%ED%8A%B9%EB%B3%84%EC%8B%9C-%EB%8F%99%EB%8C%80%EB%AC%B8%EA%B5%AC-%EC%A0%9C%EA%B8%B0%EB%8F%99/", "workingTime": ["-", "09:00~18:00", "09:00~20:00", "09:00~18:00", "09:00~18:00", "09:00~18:00", "09:00~14:00", "-"], "course": ["\uad6c\uac15\ub0b4\uacfc", "\uad6c\uac15\ubcd1\ub9ac\uacfc", "\uad6c\uac15\uc545\uc548\uba74\ubc29\uc0ac\uc120\uacfc", "\uad6c\uac15\uc548\uba74\uc678\uacfc", "\uc18c\uc544\uce58\uacfc", "\uc608\ubc29\uce58\uacfc", "\uce58\uacfc\uad50\uc815\uacfc", "\uce58\uacfc\ubcf4\uc874\uacfc", "\uce58\uacfc\ubcf4\ucca0\uacfc", "\uce58\uc8fc\uacfc", "\ud1b5\ud569\uce58\uc758\ud559\uacfc"]}, {"name": "\ubd80\ubaa8\ub9c8\uc74c\uce58\uacfc\uc758\uc6d0", "lat": "37.57876236859214", "lng": "127.03620412197495", "url": "/info/%EB%B6%80%EB%AA%A8%EB%A7%88%EC%9D%8C%EC%B9%98%EA%B3%BC%EC%9D%98%EC%9B%90-%EC%84%9C%EC%9A%B8%ED%8A%B9%EB%B3%84%EC%8B%9C-%EB%8F%99%EB%8C%80%EB%AC%B8%EA%B5%AC-%EC%A0%9C%EA%B8%B0%EB%8F%99/", "workingTime": ["-", "09:30~18:30", "09:30~18:30", "09:30~18:30", "09:30~20:30", "09:30~18:00", "10:00~14:00", "-"], "course": ["\uce58\uacfc", "\ud1b5\ud569\uce58\uc758\ud559\uacfc"]}, {"name": "\uad7f\ubaa8\ub2dd\uce58\uacfc\uc758\uc6d0", "lat": "37.57842690195145", "lng": "127.03715943611789", "url": "/info/%EA%B5%BF%EB%AA%A8%EB%8B%9D%EC%B9%98%EA%B3%BC%EC%9D%98%EC%9B%90-%EC%84%9C%EC%9A%B8%ED%8A%B9%EB%B3%84%EC%8B%9C-%EB%8F%99%EB%8C%80%EB%AC%B8%EA%B5%AC-%EC%A0%9C%EA%B8%B0%EB%8F%99/", "workingTime": ["-", "09:30~18:30", "09:30~18:30", "09:30~13:00", "09:30~18:30", "09:30~18:30", "09:30~13:30", "-"], "course": ["\uce58\uacfc"]}, {"name": "\uace8\uc778\ud55c\uc758\uc6d0", "lat": "37.581763888888887", "lng": "127.037211111111105", "url": "/info/%EA%B3%A8%EC%9D%B8%ED%95%9C%EC%9D%98%EC%9B%90-%EC%84%9C%EC%9A%B8%ED%8A%B9%EB%B3%84%EC%8B%9C-%EB%8F%99%EB%8C%80%EB%AC%B8%EA%B5%AC-%EC%A0%9C%EA%B8%B0%EB%8F%99/", "workingTime": ["-", "10:00~18:00", "10:00~18:00", "10:00~18:00", "10:00~18:00", "10:00~18:00", "10:00~13:00", "-"], "course": ["\uc0ac\uc0c1\uccb4\uc9c8\uacfc", "\uce68\uad6c\uacfc", "\ud55c\ubc29\ub0b4\uacfc", "\ud55c\ubc29\ubd80\uc778\uacfc", "\ud55c\ubc29\uc18c\uc544\uacfc", "\ud55c\ubc29\uc2e0\uacbd\uc815\uc2e0\uacfc", "\ud55c\ubc29\uc548\uc774\ube44\uc778\ud6c4\ud53c\ubd80\uacfc", "\ud55c\ubc29\uc7ac\ud65c\uc758\ud559\uacfc"]}, {"name": "\uacbd\ub3d9\uc218\uce58\uacfc\uc758\uc6d0", "lat": "37.5800591790677", "lng": "127.03817461426728", "url": "/info/%EA%B2%BD%EB%8F%99%EC%88%98%EC%B9%98%EA%B3%BC%EC%9D%98%EC%9B%90-%EC%84%9C%EC%9A%B8%ED%8A%B9%EB%B3%84%EC%8B%9C-%EB%8F%99%EB%8C%80%EB%AC%B8%EA%B5%AC-%EC%A0%9C%EA%B8%B0%EB%8F%99/", "workingTime": ["-", "09:00~18:00", "09:00~20:00", "09:00~18:00", "09:00~18:00", "09:00~18:00", "09:00~14:00", "-"], "course": ["\uad6c\uac15\ub0b4\uacfc", "\uad6c\uac15\ubcd1\ub9ac\uacfc", "\uad6c\uac15\uc545\uc548\uba74\ubc29\uc0ac\uc120\uacfc", "\uad6c\uac15\uc548\uba74\uc678\uacfc", "\uc608\ubc29\uce58\uacfc", "\uce58\uacfc\uad50\uc815\uacfc", "\uce58\uacfc\ubcf4\uc874\uacfc", "\uce58\uacfc\ubcf4\ucca0\uacfc", "\uce58\uc8fc\uacfc"]}, {"name": "\ub9bc\ud50c\ub780\ud2b8\uce58\uacfc\uc758\uc6d0", "lat": "37.578448405455994", "lng": "127.03753982621164", "url": "/info/%EB%A6%BC%ED%94%8C%EB%9E%80%ED%8A%B8%EC%B9%98%EA%B3%BC%EC%9D%98%EC%9B%90-%EC%84%9C%EC%9A%B8%ED%8A%B9%EB%B3%84%EC%8B%9C-%EB%8F%99%EB%8C%80%EB%AC%B8%EA%B5%AC-%EC%A0%9C%EA%B8%B0%EB%8F%99/", "workingTime": ["-", "09:00~18:00", "09:00~18:00", "09:00~18:00", "09:00~18:00", "09:00~18:00", "09:00~13:00", "-"], "course": ["\uad6c\uac15\ub0b4\uacfc", "\uad6c\uac15\uc548\uba74\uc678\uacfc", "\uc18c\uc544\uce58\uacfc", "\uc608\ubc29\uce58\uacfc", "\uce58\uacfc\uad50\uc815\uacfc", "\uce58\uacfc\ubcf4\uc874\uacfc", "\uce58\uacfc\ubcf4\ucca0\uacfc", "\uce58\uc8fc\uacfc", "\ud1b5\ud569\uce58\uc758\ud559\uacfc"]}, {"name": "\ub3d9\ub300\ubb38\ub098\ub214\uce58\uacfc\uc758\uc6d0", "lat": "37.5785884053", "lng": "127.0392470787", "url": "/info/%EB%8F%99%EB%8C%80%EB%AC%B8%EB%82%98%EB%88%94%EC%B9%98%EA%B3%BC%EC%9D%98%EC%9B%90-%EC%84%9C%EC%9A%B8%ED%8A%B9%EB%B3%84%EC%8B%9C-%EB%8F%99%EB%8C%80%EB%AC%B8%EA%B5%AC-%EC%A0%9C%EA%B8%B0%EB%8F%99/", "workingTime": ["-", "09:30~18:30", "09:30~18:30", "09:30~18:30", "09:30~18:30", "09:30~18:30", "09:30~14:00", "-"], "course": ["\uce58\uacfc"]}, {"name": "\uc911\uc559\uce58\uacfc\uc758\uc6d0", "lat": "37.579486343894", "lng": "127.042100208729", "url": "/info/%EC%A4%91%EC%95%99%EC%B9%98%EA%B3%BC%EC%9D%98%EC%9B%90-%EC%84%9C%EC%9A%B8%ED%8A%B9%EB%B3%84%EC%8B%9C-%EB%8F%99%EB%8C%80%EB%AC%B8%EA%B5%AC-%EC%A0%9C%EA%B8%B0%EB%8F%99/", "workingTime": ["-", "09:30~18:30", "09:30~18:30", "09:30~18:30", "09:30~18:30", "09:30~18:30", "09:30~13:30", "-"], "course": ["\uad6c\uac15\ub0b4\uacfc", "\uad6c\uac15\ubcd1\ub9ac\uacfc", "\uad6c\uac15\uc545\uc548\uba74\ubc29\uc0ac\uc120\uacfc", "\uad6c\uac15\uc548\uba74\uc678\uacfc", "\uc18c\uc544\uce58\uacfc", "\uc608\ubc29\uce58\uacfc", "\uce58\uacfc", "\uce58\uacfc\uad50\uc815\uacfc", "\uce58\uacfc\ubcf4\uc874\uacfc", "\uce58\uacfc\ubcf4\ucca0\uacfc", "\uce58\uc8fc\uacfc", "\ud1b5\ud569\uce58\uc758\ud559\uacfc"]}, {"name": "\uc11c\uc6b8\uc218\uc774\ube44\uc778\ud6c4\uacfc\uc758\uc6d0", "lat": "37.5794848121", "lng": "127.0421004343", "url": "/info/%EC%84%9C%EC%9A%B8%EC%88%98%EC%9D%B4%EB%B9%84%EC%9D%B8%ED%9B%84%EA%B3%BC%EC%9D%98%EC%9B%90-%EC%84%9C%EC%9A%B8%ED%8A%B9%EB%B3%84%EC%8B%9C-%EB%8F%99%EB%8C%80%EB%AC%B8%EA%B5%AC-%EC%A0%9C%EA%B8%B0%EB%8F%99/", "workingTime": ["-", "09:00~18:00", "09:00~18:00", "09:00~18:00", "09:00~18:00", "09:00~18:00", "09:00~13:00", "-"], "course": ["\ub0b4\uacfc", "\uc131\ud615\uc678\uacfc", "\uc18c\uc544\uccad\uc18c\ub144\uacfc", "\uc678\uacfc", "\uc774\ube44\uc778\ud6c4\uacfc"]}, {"name": "\uc11c\uc6b8\ub098\uc740\ubcd1\uc6d0", "lat": "37.578600653495414", "lng": "127.03885290640591", "url": "/info/%EC%84%9C%EC%9A%B8%EB%82%98%EC%9D%80%EB%B3%91%EC%9B%90-%EC%84%9C%EC%9A%B8%ED%8A%B9%EB%B3%84%EC%8B%9C-%EB%8F%99%EB%8C%80%EB%AC%B8%EA%B5%AC-%EC%A0%9C%EA%B8%B0%EB%8F%99/", "workingTime": ["-", "09:00~17:30", "09:00~17:30", "09:00~17:30", "09:00~17:30", "09:00~17:30", "09:00~13:00", "-"], "course": ["\ub0b4\uacfc", "\ub9c8\ucde8\ud1b5\uc99d\uc758\ud559\uacfc", "\uc2e0\uacbd\uc678\uacfc", "\uc601\uc0c1\uc758\ud559\uacfc", "\uc815\ud615\uc678\uacfc"]}, {"name": "\uc5f0\uc138\uc815\ub0b4\uacfc\uc758\uc6d0", "lat": "37.582483361586405", "lng": "127.03017841690177", "url": "/info/%EC%97%B0%EC%84%B8%EC%A0%95%EB%82%B4%EA%B3%BC%EC%9D%98%EC%9B%90-%EC%84%9C%EC%9A%B8%ED%8A%B9%EB%B3%84%EC%8B%9C-%EB%8F%99%EB%8C%80%EB%AC%B8%EA%B5%AC-%EC%A0%9C%EA%B8%B0%EB%8F%99/", "workingTime": ["-", "09:00~18:30", "09:00~18:30", "09:00~18:30", "09:00~18:30", "09:00~18:30", "09:00~15:00", "-"], "course": ["\ub0b4\uacfc", "\uc18c\uc544\uccad\uc18c\ub144\uacfc", "\uc678\uacfc", "\uc774\ube44\uc778\ud6c4\uacfc", "\ud53c\ubd80\uacfc"]}, {"name": "\uc81c\uc77c\uc815\ud615\uc678\uacfc\uc758\uc6d0", "lat": "37.5797739940038", "lng": "127.042953862107", "url": "/info/%EC%A0%9C%EC%9D%BC%EC%A0%95%ED%98%95%EC%99%B8%EA%B3%BC%EC%9D%98%EC%9B%90-%EC%84%9C%EC%9A%B8%ED%8A%B9%EB%B3%84%EC%8B%9C-%EB%8F%99%EB%8C%80%EB%AC%B8%EA%B5%AC-%EC%A0%9C%EA%B8%B0%EB%8F%99/", "workingTime": ["-", "09:00~19:00", "09:00~19:00", "09:00~19:00", "09:00~19:00", "09:00~19:00", "09:00~14:00", "-"], "course": ["\uac00\uc815\uc758\ud559\uacfc", "\ub0b4\uacfc", "\ub9c8\ucde8\ud1b5\uc99d\uc758\ud559\uacfc", "\ube44\ub1e8\uc758\ud559\uacfc", "\uc18c\uc544\uccad\uc18c\ub144\uacfc", "\uc2e0\uacbd\uacfc", "\uc2e0\uacbd\uc678\uacfc", "\uc678\uacfc", "\uc774\ube44\uc778\ud6c4\uacfc", "\uc7ac\ud65c\uc758\ud559\uacfc", "\uc815\ud615\uc678\uacfc", "\ud53c\ubd80\uacfc", "\ud749\ubd80\uc678\uacfc"]}, {"name": "\uc6b0\ud0dc\ud558\ud53c\ubd80\uacfc\uc758\uc6d0\ub3d9\ub300\ubb38\uc810", "lat": "37.5788570401089", "lng": "127.040174173148", "url": "/info/%EC%9A%B0%ED%83%9C%ED%95%98%ED%94%BC%EB%B6%80%EA%B3%BC%EC%9D%98%EC%9B%90%EB%8F%99%EB%8C%80%EB%AC%B8%EC%A0%90-%EC%84%9C%EC%9A%B8%ED%8A%B9%EB%B3%84%EC%8B%9C-%EB%8F%99%EB%8C%80%EB%AC%B8%EA%B5%AC-%EC%A0%9C%EA%B8%B0%EB%8F%99/", "workingTime": ["-", "09:30~19:00", "09:30~19:00", "09:30~13:00", "09:30~19:00", "09:30~19:00", "09:00~12:30", "-"], "course": ["\ud53c\ubd80\uacfc"]}, {"name": "\uc11c\uc6b8\uc815\ud615\uc678\uacfc\uc758\uc6d0", "lat": "37.58213483307962", "lng": "127.03889571346191", "url": "/info/%EC%84%9C%EC%9A%B8%EC%A0%95%ED%98%95%EC%99%B8%EA%B3%BC%EC%9D%98%EC%9B%90-%EC%84%9C%EC%9A%B8%ED%8A%B9%EB%B3%84%EC%8B%9C-%EB%8F%99%EB%8C%80%EB%AC%B8%EA%B5%AC-%EC%A0%9C%EA%B8%B0%EB%8F%99/", "workingTime": ["-", "09:00~18:30", "09:00~18:30", "09:00~18:30", "09:00~18:30", "09:00~18:30", "09:00~13:00", "-"], "course": ["\ub0b4\uacfc", "\ube44\ub1e8\uc758\ud559\uacfc", "\uc2e0\uacbd\uc678\uacfc", "\uc678\uacfc", "\uc815\ud615\uc678\uacfc", "\ud53c\ubd80\uacfc"]}, {"name": "\uc57d\ucd08\ub2f9\ud55c\uc758\uc6d0", "lat": "37.587991666666667", "lng": "127.034641666666673", "url": "/info/%EC%95%BD%EC%B4%88%EB%8B%B9%ED%95%9C%EC%9D%98%EC%9B%90-%EC%84%9C%EC%9A%B8%ED%8A%B9%EB%B3%84%EC%8B%9C-%EB%8F%99%EB%8C%80%EB%AC%B8%EA%B5%AC-%EC%A0%9C%EA%B8%B0%EB%8F%99/", "workingTime": ["-", "10:00~18:00", "10:00~18:00", "10:00~18:00", "10:00~18:00", "10:00~18:00", "10:00~13:00", "-"], "course": ["\uc0ac\uc0c1\uccb4\uc9c8\uacfc", "\uce68\uad6c\uacfc", "\ud55c\ubc29\ub0b4\uacfc", "\ud55c\ubc29\ubd80\uc778\uacfc", "\ud55c\ubc29\uc18c\uc544\uacfc", "\ud55c\ubc29\uc2e0\uacbd\uc815\uc2e0\uacfc", "\ud55c\ubc29\uc548\uc774\ube44\uc778\ud6c4\ud53c\ubd80\uacfc", "\ud55c\ubc29\uc7ac\ud65c\uc758\ud559\uacfc"]}, {"name": "\uc624\ucc3d\uc900\uc678\uacfc\uc758\uc6d0", "lat": "37.5910984571", "lng": "127.037197439", "url": "/info/%EC%98%A4%EC%B0%BD%EC%A4%80%EC%99%B8%EA%B3%BC%EC%9D%98%EC%9B%90-%EC%84%9C%EC%9A%B8%ED%8A%B9%EB%B3%84%EC%8B%9C-%EB%8F%99%EB%8C%80%EB%AC%B8%EA%B5%AC-%EC%A0%9C%EA%B8%B0%EB%8F%99/", "workingTime": ["-", "09:00~18:00", "09:00~18:00", "09:00~13:00", "09:00~18:00", "09:00~18:00", "-", "-"], "course": ["\ub0b4\uacfc", "\ube44\ub1e8\uc758\ud559\uacfc", "\uc18c\uc544\uccad\uc18c\ub144\uacfc", "\uc678\uacfc", "\uc7ac\ud65c\uc758\ud559\uacfc"]}, {"name": "\ud669\uc0b0\ud55c\uc758\uc6d0", "lat": "37.58191518761755", "lng": "127.03829330387289", "url": "/info/%ED%99%A9%EC%82%B0%ED%95%9C%EC%9D%98%EC%9B%90-%EC%84%9C%EC%9A%B8%ED%8A%B9%EB%B3%84%EC%8B%9C-%EB%8F%99%EB%8C%80%EB%AC%B8%EA%B5%AC-%EC%A0%9C%EA%B8%B0%EB%8F%99/", "workingTime": ["-", "09:00~18:00", "09:00~18:00", "09:00~18:00", "09:00~18:00", "09:00~18:00", "09:00~14:00", "-"], "course": ["\uc0ac\uc0c1\uccb4\uc9c8\uacfc", "\uce68\uad6c\uacfc", "\ud55c\ubc29\ub0b4\uacfc", "\ud55c\ubc29\ubd80\uc778\uacfc", "\ud55c\ubc29\uc18c\uc544\uacfc", "\ud55c\ubc29\uc2e0\uacbd\uc815\uc2e0\uacfc", "\ud55c\ubc29\uc548\uc774\ube44\uc778\ud6c4\ud53c\ubd80\uacfc", "\ud55c\ubc29\uc7ac\ud65c\uc758\ud559\uacfc"]}, {"name": "\uc655\uc790\ud55c\uc758\uc6d0", "lat": "37.579231752075145", "lng": "127.03754000374032", "url": "/info/%EC%99%95%EC%9E%90%ED%95%9C%EC%9D%98%EC%9B%90-%EC%84%9C%EC%9A%B8%ED%8A%B9%EB%B3%84%EC%8B%9C-%EB%8F%99%EB%8C%80%EB%AC%B8%EA%B5%AC-%EC%A0%9C%EA%B8%B0%EB%8F%99/", "workingTime": ["-", "10:00~16:00", "10:00~16:00", "-", "10:00~16:00", "10:00~16:00", "10:00~16:00", "-"], "course": ["\uc0ac\uc0c1\uccb4\uc9c8\uacfc", "\uce68\uad6c\uacfc", "\ud55c\ubc29\ub0b4\uacfc", "\ud55c\ubc29\ubd80\uc778\uacfc", "\ud55c\ubc29\uc18c\uc544\uacfc", "\ud55c\ubc29\uc2e0\uacbd\uc815\uc2e0\uacfc", "\ud55c\ubc29\uc548\uc774\ube44\uc778\ud6c4\ud53c\ubd80\uacfc", "\ud55c\ubc29\uc7ac\ud65c\uc758\ud559\uacfc"]}, {"name": "\ube5b\ud55c\uc758\uc6d0", "lat": "37.5792248443783", "lng": "127.036511029987", "url": "/info/%EB%B9%9B%ED%95%9C%EC%9D%98%EC%9B%90-%EC%84%9C%EC%9A%B8%ED%8A%B9%EB%B3%84%EC%8B%9C-%EB%8F%99%EB%8C%80%EB%AC%B8%EA%B5%AC-%EC%A0%9C%EA%B8%B0%EB%8F%99/", "workingTime": ["-", "09:00~18:00", "09:00~18:00", "09:00~18:00", "09:00~18:00", "09:00~18:00", "09:00~13:00", "-"], "course": ["\uc0ac\uc0c1\uccb4\uc9c8\uacfc", "\uce68\uad6c\uacfc", "\ud55c\ubc29\ub0b4\uacfc", "\ud55c\ubc29\ubd80\uc778\uacfc", "\ud55c\ubc29\uc18c\uc544\uacfc", "\ud55c\ubc29\uc2e0\uacbd\uc815\uc2e0\uacfc", "\ud55c\ubc29\uc548\uc774\ube44\uc778\ud6c4\ud53c\ubd80\uacfc", "\ud55c\ubc29\uc7ac\ud65c\uc758\ud559\uacfc"]}, {"name": "\uc11c\uc6b8\ub3d9\uc11c\ub0a8\ubd81\uce58\uacfc\uc758\uc6d0", "lat": "37.5784958557261", "lng": "127.036492900333", "url": "/info/%EC%84%9C%EC%9A%B8%EB%8F%99%EC%84%9C%EB%82%A8%EB%B6%81%EC%B9%98%EA%B3%BC%EC%9D%98%EC%9B%90-%EC%84%9C%EC%9A%B8%ED%8A%B9%EB%B3%84%EC%8B%9C-%EB%8F%99%EB%8C%80%EB%AC%B8%EA%B5%AC-%EC%A0%9C%EA%B8%B0%EB%8F%99/", "workingTime": ["1,2,3,4,5\uc9f8\uc8fc09:00~14:00", "09:00~18:00", "09:00~20:00", "09:00~20:00", "09:00~18:00", "09:00~18:00", "09:00~14:00", "-"], "course": ["\uad6c\uac15\ub0b4\uacfc", "\uad6c\uac15\ubcd1\ub9ac\uacfc", "\uad6c\uac15\uc545\uc548\uba74\ubc29\uc0ac\uc120\uacfc", "\uad6c\uac15\uc548\uba74\uc678\uacfc", "\uc18c\uc544\uce58\uacfc", "\uc608\ubc29\uce58\uacfc", "\uce58\uacfc\uad50\uc815\uacfc", "\uce58\uacfc\ubcf4\uc874\uacfc", "\uce58\uacfc\ubcf4\ucca0\uacfc", "\uce58\uc8fc\uacfc", "\ud1b5\ud569\uce58\uc758\ud559\uacfc"]}, {"name": "\uacbd\ud654\uace0\ub824\ub2f9\ud55c\uc758\uc6d0", "lat": "37.5789927744838", "lng": "127.03700575312436", "url": "/info/%EA%B2%BD%ED%99%94%EA%B3%A0%EB%A0%A4%EB%8B%B9%ED%95%9C%EC%9D%98%EC%9B%90-%EC%84%9C%EC%9A%B8%ED%8A%B9%EB%B3%84%EC%8B%9C-%EB%8F%99%EB%8C%80%EB%AC%B8%EA%B5%AC-%EC%A0%9C%EA%B8%B0%EB%8F%99/", "workingTime": ["-", "10:00~17:00", "10:00~17:00", "10:00~17:00", "10:00~17:00", "10:00~17:00", "10:00~17:00", "-"], "course": ["\uce68\uad6c\uacfc", "\ud55c\ubc29\ub0b4\uacfc", "\ud55c\ubc29\ubd80\uc778\uacfc", "\ud55c\ubc29\uc18c\uc544\uacfc", "\ud55c\ubc29\uc2e0\uacbd\uc815\uc2e0\uacfc", "\ud55c\ubc29\uc548\uc774\ube44\uc778\ud6c4\ud53c\ubd80\uacfc"]}, {"name": "\uccad\ub7c9\ub9ac\uc5f0\uc138\uc81c\uc77c\uce58\uacfc\uc758\uc6d0", "lat": "37.5797739940038", "lng": "127.042953862107", "url": "/info/%EC%B2%AD%EB%9F%89%EB%A6%AC%EC%97%B0%EC%84%B8%EC%A0%9C%EC%9D%BC%EC%B9%98%EA%B3%BC%EC%9D%98%EC%9B%90-%EC%84%9C%EC%9A%B8%ED%8A%B9%EB%B3%84%EC%8B%9C-%EB%8F%99%EB%8C%80%EB%AC%B8%EA%B5%AC-%EC%A0%9C%EA%B8%B0%EB%8F%99/", "workingTime": ["-", "09:00~18:00", "09:00~18:00", "09:00~20:00", "09:00~18:00", "09:00~18:00", "09:00~13:30", "-"], "course": ["\uad6c\uac15\ub0b4\uacfc", "\uad6c\uac15\ubcd1\ub9ac\uacfc", "\uad6c\uac15\uc545\uc548\uba74\ubc29\uc0ac\uc120\uacfc", "\uad6c\uac15\uc548\uba74\uc678\uacfc", "\uc18c\uc544\uce58\uacfc", "\uc608\ubc29\uce58\uacfc", "\uce58\uacfc\uad50\uc815\uacfc", "\uce58\uacfc\ubcf4\uc874\uacfc", "\uce58\uacfc\ubcf4\ucca0\uacfc", "\uce58\uc8fc\uacfc", "\ud1b5\ud569\uce58\uc758\ud559\uacfc"]}, {"name": "\ud3c9\ud654\ud55c\uc758\uc6d0", "lat": "37.57936143872723", "lng": "127.03772120000966", "url": "/info/%ED%8F%89%ED%99%94%ED%95%9C%EC%9D%98%EC%9B%90-%EC%84%9C%EC%9A%B8%ED%8A%B9%EB%B3%84%EC%8B%9C-%EB%8F%99%EB%8C%80%EB%AC%B8%EA%B5%AC-%EC%A0%9C%EA%B8%B0%EB%8F%99/", "workingTime": ["-", "09:00~18:00", "09:00~18:00", "09:00~18:00", "09:00~18:00", "09:00~18:00", "09:00~16:00", "09:00~18:00"], "course": ["\uce68\uad6c\uacfc", "\ud55c\ubc29\ub0b4\uacfc", "\ud55c\ubc29\ubd80\uc778\uacfc", "\ud55c\ubc29\uc18c\uc544\uacfc", "\ud55c\ubc29\uc2e0\uacbd\uc815\uc2e0\uacfc", "\ud55c\ubc29\uc548\uc774\ube44\uc778\ud6c4\ud53c\ubd80\uacfc"]}, {"name": "\ub3d9\uad11\ub2f9\ud55c\uc758\uc6d0", "lat": "37.5815225295", "lng": "127.0377496813", "url": "/info/%EB%8F%99%EA%B4%91%EB%8B%B9%ED%95%9C%EC%9D%98%EC%9B%90-%EC%84%9C%EC%9A%B8%ED%8A%B9%EB%B3%84%EC%8B%9C-%EB%8F%99%EB%8C%80%EB%AC%B8%EA%B5%AC-%EC%A0%9C%EA%B8%B0%EB%8F%99/", "workingTime": ["-", "10:00~18:00", "10:00~18:00", "10:00~18:00", "10:00~18:00", "10:00~18:00", "10:00~13:00", "-"], "course": ["\uc0ac\uc0c1\uccb4\uc9c8\uacfc", "\uce68\uad6c\uacfc", "\ud55c\ubc29\ub0b4\uacfc", "\ud55c\ubc29\ubd80\uc778\uacfc", "\ud55c\ubc29\uc18c\uc544\uacfc", "\ud55c\ubc29\uc2e0\uacbd\uc815\uc2e0\uacfc", "\ud55c\ubc29\uc548\uc774\ube44\uc778\ud6c4\ud53c\ubd80\uacfc", "\ud55c\ubc29\uc7ac\ud65c\uc758\ud559\uacfc"]}, {"name": "\ub3d9\uad11\ud55c\uc758\uc6d0", "lat": "37.57884154495035", "lng": "127.03655286396948", "url": "/info/%EB%8F%99%EA%B4%91%ED%95%9C%EC%9D%98%EC%9B%90-%EC%84%9C%EC%9A%B8%ED%8A%B9%EB%B3%84%EC%8B%9C-%EB%8F%99%EB%8C%80%EB%AC%B8%EA%B5%AC-%EC%A0%9C%EA%B8%B0%EB%8F%99/", "workingTime": ["2,4\uc9f8\uc8fc09:30~17:00", "09:30~18:00", "09:30~18:00", "10:00~18:00", "-", "09:30~18:00", "09:30~17:00", "-"], "course": ["\uc0ac\uc0c1\uccb4\uc9c8\uacfc", "\uce68\uad6c\uacfc", "\ud55c\ubc29\ub0b4\uacfc", "\ud55c\ubc29\ubd80\uc778\uacfc", "\ud55c\ubc29\uc18c\uc544\uacfc", "\ud55c\ubc29\uc2e0\uacbd\uc815\uc2e0\uacfc", "\ud55c\ubc29\uc548\uc774\ube44\uc778\ud6c4\ud53c\ubd80\uacfc", "\ud55c\ubc29\uc7ac\ud65c\uc758\ud559\uacfc"]}, {"name": "\uc624\uc131\ud55c\uc758\uc6d0", "lat": "37.5785867839247", "lng": "127.039245719345", "url": "/info/%EC%98%A4%EC%84%B1%ED%95%9C%EC%9D%98%EC%9B%90-%EC%84%9C%EC%9A%B8%ED%8A%B9%EB%B3%84%EC%8B%9C-%EB%8F%99%EB%8C%80%EB%AC%B8%EA%B5%AC-%EC%A0%9C%EA%B8%B0%EB%8F%99/", "workingTime": ["-", "10:00~18:00", "10:00~21:00", "10:00~18:00", "10:00~18:00", "10:00~18:00", "10:00~14:00", "10:00~18:00"], "course": ["\uc0ac\uc0c1\uccb4\uc9c8\uacfc", "\uce68\uad6c\uacfc", "\ud55c\ubc29\ub0b4\uacfc", "\ud55c\ubc29\ubd80\uc778\uacfc", "\ud55c\ubc29\uc18c\uc544\uacfc", "\ud55c\ubc29\uc2e0\uacbd\uc815\uc2e0\uacfc", "\ud55c\ubc29\uc548\uc774\ube44\uc778\ud6c4\ud53c\ubd80\uacfc", "\ud55c\ubc29\uc7ac\ud65c\uc758\ud559\uacfc"]}, {"name": "\ud0dc\uc601\ub2f9\ud55c\uc758\uc6d0", "lat": "37.57866107309525", "lng": "127.0374357811813", "url": "/info/%ED%83%9C%EC%98%81%EB%8B%B9%ED%95%9C%EC%9D%98%EC%9B%90-%EC%84%9C%EC%9A%B8%ED%8A%B9%EB%B3%84%EC%8B%9C-%EB%8F%99%EB%8C%80%EB%AC%B8%EA%B5%AC-%EC%A0%9C%EA%B8%B0%EB%8F%99/", "workingTime": ["-", "09:00~19:00", "09:00~19:00", "09:00~19:00", "09:00~19:00", "09:00~19:00", "09:00~18:00", "09:00~18:00"], "course": ["\uc0ac\uc0c1\uccb4\uc9c8\uacfc", "\uce68\uad6c\uacfc", "\ud55c\ubc29\ub0b4\uacfc", "\ud55c\ubc29\ubd80\uc778\uacfc", "\ud55c\ubc29\uc18c\uc544\uacfc", "\ud55c\ubc29\uc2e0\uacbd\uc815\uc2e0\uacfc", "\ud55c\ubc29\uc548\uc774\ube44\uc778\ud6c4\ud53c\ubd80\uacfc", "\ud55c\ubc29\uc7ac\ud65c\uc758\ud559\uacfc"]}, {"name": "\ubcf4\uc0dd\ub2f9\ud55c\uc758\uc6d0", "lat": "37.5793855051", "lng": "127.0373319911", "url": "/info/%EB%B3%B4%EC%83%9D%EB%8B%B9%ED%95%9C%EC%9D%98%EC%9B%90-%EC%84%9C%EC%9A%B8%ED%8A%B9%EB%B3%84%EC%8B%9C-%EB%8F%99%EB%8C%80%EB%AC%B8%EA%B5%AC-%EC%A0%9C%EA%B8%B0%EB%8F%99/", "workingTime": ["-", "09:00~18:00", "09:00~18:00", "09:00~18:00", "09:00~18:00", "09:00~18:00", "09:00~18:00", "09:00~18:00"], "course": ["\uc0ac\uc0c1\uccb4\uc9c8\uacfc", "\uce68\uad6c\uacfc", "\ud55c\ubc29\ub0b4\uacfc", "\ud55c\ubc29\ubd80\uc778\uacfc", "\ud55c\ubc29\uc18c\uc544\uacfc", "\ud55c\ubc29\uc2e0\uacbd\uc815\uc2e0\uacfc", "\ud55c\ubc29\uc548\uc774\ube44\uc778\ud6c4\ud53c\ubd80\uacfc", "\ud55c\ubc29\uc7ac\ud65c\uc758\ud559\uacfc"]}, {"name": "\ub3c4\uc77c\ud55c\uc758\uc6d0", "lat": "37.57878288222235", "lng": "127.03965926030687", "url": "/info/%EB%8F%84%EC%9D%BC%ED%95%9C%EC%9D%98%EC%9B%90-%EC%84%9C%EC%9A%B8%ED%8A%B9%EB%B3%84%EC%8B%9C-%EB%8F%99%EB%8C%80%EB%AC%B8%EA%B5%AC-%EC%A0%9C%EA%B8%B0%EB%8F%99/", "workingTime": ["-", "09:00~18:30", "09:00~18:30", "09:00~18:30", "09:00~18:30", "09:00~18:30", "09:00~14:00", "-"], "course": ["\uc0ac\uc0c1\uccb4\uc9c8\uacfc", "\uce68\uad6c\uacfc", "\ud55c\ubc29\ub0b4\uacfc", "\ud55c\ubc29\ubd80\uc778\uacfc", "\ud55c\ubc29\uc18c\uc544\uacfc", "\ud55c\ubc29\uc2e0\uacbd\uc815\uc2e0\uacfc", "\ud55c\ubc29\uc548\uc774\ube44\uc778\ud6c4\ud53c\ubd80\uacfc", "\ud55c\ubc29\uc751\uae09\uacfc", "\ud55c\ubc29\uc7ac\ud65c\uc758\ud559\uacfc"]}, {"name": "\ucc38\uc870\uc740\ud55c\uc758\uc6d0", "lat": "37.580643016442465", "lng": "127.03818398998358", "url": "/info/%EC%B0%B8%EC%A1%B0%EC%9D%80%ED%95%9C%EC%9D%98%EC%9B%90-%EC%84%9C%EC%9A%B8%ED%8A%B9%EB%B3%84%EC%8B%9C-%EB%8F%99%EB%8C%80%EB%AC%B8%EA%B5%AC-%EC%A0%9C%EA%B8%B0%EB%8F%99/", "workingTime": ["-", "10:00~18:00", "10:00~18:00", "10:00~18:00", "10:00~18:00", "10:00~18:00", "10:00~16:00", "10:00~18:00"], "course": ["\uc0ac\uc0c1\uccb4\uc9c8\uacfc", "\uce68\uad6c\uacfc", "\ud55c\ubc29\ub0b4\uacfc", "\ud55c\ubc29\ubd80\uc778\uacfc", "\ud55c\ubc29\uc18c\uc544\uacfc", "\ud55c\ubc29\uc2e0\uacbd\uc815\uc2e0\uacfc", "\ud55c\ubc29\uc548\uc774\ube44\uc778\ud6c4\ud53c\ubd80\uacfc", "\ud55c\ubc29\uc7ac\ud65c\uc758\ud559\uacfc"]}, {"name": "\uad11\uba85\ub2f9\ud55c\uc758\uc6d0", "lat": "37.579039605474826", "lng": "127.03706013734761", "url": "/info/%EA%B4%91%EB%AA%85%EB%8B%B9%ED%95%9C%EC%9D%98%EC%9B%90-%EC%84%9C%EC%9A%B8%ED%8A%B9%EB%B3%84%EC%8B%9C-%EB%8F%99%EB%8C%80%EB%AC%B8%EA%B5%AC-%EC%A0%9C%EA%B8%B0%EB%8F%99/", "workingTime": ["-", "10:00~18:00", "10:00~18:00", "10:00~18:00", "10:00~18:00", "10:00~18:00", "10:00~18:00", "10:00~18:00"], "course": ["\uc0ac\uc0c1\uccb4\uc9c8\uacfc", "\uce68\uad6c\uacfc", "\ud55c\ubc29\ub0b4\uacfc", "\ud55c\ubc29\ubd80\uc778\uacfc", "\ud55c\ubc29\uc18c\uc544\uacfc", "\ud55c\ubc29\uc2e0\uacbd\uc815\uc2e0\uacfc", "\ud55c\ubc29\uc548\uc774\ube44\uc778\ud6c4\ud53c\ubd80\uacfc", "\ud55c\ubc29\uc7ac\ud65c\uc758\ud559\uacfc"]}, {"name": "\uacbd\ud76c\ubd80\ud765\ud55c\uc758\uc6d0", "lat": "37.5788728549979", "lng": "127.036996750279", "url": "/info/%EA%B2%BD%ED%9D%AC%EB%B6%80%ED%9D%A5%ED%95%9C%EC%9D%98%EC%9B%90-%EC%84%9C%EC%9A%B8%ED%8A%B9%EB%B3%84%EC%8B%9C-%EB%8F%99%EB%8C%80%EB%AC%B8%EA%B5%AC-%EC%A0%9C%EA%B8%B0%EB%8F%99/", "workingTime": ["1,2,3,4,5\uc9f8\uc8fc09:30~17:00", "09:30~17:00", "09:30~17:00", "-", "09:30~17:00", "09:30~17:00", "09:30~17:00", "09:30~17:00"], "course": ["\uce68\uad6c\uacfc", "\ud55c\ubc29\ub0b4\uacfc", "\ud55c\ubc29\ubd80\uc778\uacfc", "\ud55c\ubc29\uc18c\uc544\uacfc", "\ud55c\ubc29\uc2e0\uacbd\uc815\uc2e0\uacfc", "\ud55c\ubc29\uc548\uc774\ube44\uc778\ud6c4\ud53c\ubd80\uacfc", "\ud55c\ubc29\uc7ac\ud65c\uc758\ud559\uacfc"]}, {"name": "\ubd80\uc0b0\ud55c\uc758\uc6d0", "lat": "37.57842690195145", "lng": "127.03715943611789", "url": "/info/%EB%B6%80%EC%82%B0%ED%95%9C%EC%9D%98%EC%9B%90-%EC%84%9C%EC%9A%B8%ED%8A%B9%EB%B3%84%EC%8B%9C-%EB%8F%99%EB%8C%80%EB%AC%B8%EA%B5%AC-%EC%A0%9C%EA%B8%B0%EB%8F%99/", "workingTime": ["2,4,5\uc9f8\uc8fc10:30~17:30", "10:30~17:30", "10:30~17:30", "10:30~17:30", "10:30~17:30", "10:30~17:30", "10:30~17:30", "10:30~17:30"], "course": ["\uc0ac\uc0c1\uccb4\uc9c8\uacfc", "\uce68\uad6c\uacfc", "\ud55c\ubc29\ub0b4\uacfc", "\ud55c\ubc29\ubd80\uc778\uacfc", "\ud55c\ubc29\uc18c\uc544\uacfc", "\ud55c\ubc29\uc2e0\uacbd\uc815\uc2e0\uacfc", "\ud55c\ubc29\uc548\uc774\ube44\uc778\ud6c4\ud53c\ubd80\uacfc", "\ud55c\ubc29\uc7ac\ud65c\uc758\ud559\uacfc"]}, {"name": "\uc720\uba85\ud55c\uc758\uc6d0", "lat": "37.5790392987237", "lng": "127.03802467831451", "url": "/info/%EC%9C%A0%EB%AA%85%ED%95%9C%EC%9D%98%EC%9B%90-%EC%84%9C%EC%9A%B8%ED%8A%B9%EB%B3%84%EC%8B%9C-%EB%8F%99%EB%8C%80%EB%AC%B8%EA%B5%AC-%EC%A0%9C%EA%B8%B0%EB%8F%99/", "workingTime": ["-", "10:00~18:00", "10:00~18:00", "10:00~18:00", "10:00~18:00", "10:00~18:00", "10:00~18:00", "10:00~18:00"], "course": ["\uc0ac\uc0c1\uccb4\uc9c8\uacfc", "\uce68\uad6c\uacfc", "\ud55c\ubc29\ub0b4\uacfc", "\ud55c\ubc29\ubd80\uc778\uacfc", "\ud55c\ubc29\uc18c\uc544\uacfc", "\ud55c\ubc29\uc2e0\uacbd\uc815\uc2e0\uacfc", "\ud55c\ubc29\uc548\uc774\ube44\uc778\ud6c4\ud53c\ubd80\uacfc", "\ud55c\ubc29\uc7ac\ud65c\uc758\ud559\uacfc"]}, {"name": "\uc548\uc554\ud55c\uc758\uc6d0", "lat": "37.582583852", "lng": "127.0317951387", "url": "/info/%EC%95%88%EC%95%94%ED%95%9C%EC%9D%98%EC%9B%90-%EC%84%9C%EC%9A%B8%ED%8A%B9%EB%B3%84%EC%8B%9C-%EB%8F%99%EB%8C%80%EB%AC%B8%EA%B5%AC-%EC%A0%9C%EA%B8%B0%EB%8F%99/", "workingTime": ["-", "09:00~18:30", "09:00~18:30", "09:00~18:30", "09:00~18:30", "09:00~18:30", "09:00~14:30", "-"], "course": ["\uc0ac\uc0c1\uccb4\uc9c8\uacfc", "\uce68\uad6c\uacfc", "\ud55c\ubc29\ub0b4\uacfc", "\ud55c\ubc29\ubd80\uc778\uacfc", "\ud55c\ubc29\uc18c\uc544\uacfc", "\ud55c\ubc29\uc2e0\uacbd\uc815\uc2e0\uacfc", "\ud55c\ubc29\uc548\uc774\ube44\uc778\ud6c4\ud53c\ubd80\uacfc", "\ud55c\ubc29\uc7ac\ud65c\uc758\ud559\uacfc"]}, {"name": "\uc18c\ucc3d\ud55c\uc758\uc6d0", "lat": "37.582326332365035", "lng": "127.03738327366948", "url": "/info/%EC%86%8C%EC%B0%BD%ED%95%9C%EC%9D%98%EC%9B%90-%EC%84%9C%EC%9A%B8%ED%8A%B9%EB%B3%84%EC%8B%9C-%EB%8F%99%EB%8C%80%EB%AC%B8%EA%B5%AC-%EC%A0%9C%EA%B8%B0%EB%8F%99/", "workingTime": ["-", "10:30~18:00", "10:30~18:00", "10:30~18:00", "10:30~18:00", "10:30~18:00", "10:30~14:00", "10:30~17:00"], "course": ["\uce68\uad6c\uacfc", "\ud55c\ubc29\ub0b4\uacfc", "\ud55c\ubc29\ubd80\uc778\uacfc", "\ud55c\ubc29\uc18c\uc544\uacfc", "\ud55c\ubc29\uc2e0\uacbd\uc815\uc2e0\uacfc", "\ud55c\ubc29\uc548\uc774\ube44\uc778\ud6c4\ud53c\ubd80\uacfc"]}, {"name": "\ub3d9\uba85\ud55c\uc758\uc6d0", "lat": "37.578397788882064", "lng": "127.03804244467557", "url": "/info/%EB%8F%99%EB%AA%85%ED%95%9C%EC%9D%98%EC%9B%90-%EC%84%9C%EC%9A%B8%ED%8A%B9%EB%B3%84%EC%8B%9C-%EB%8F%99%EB%8C%80%EB%AC%B8%EA%B5%AC-%EC%A0%9C%EA%B8%B0%EB%8F%99/", "workingTime": ["-", "09:30~17:00", "09:30~17:00", "09:30~17:00", "09:30~17:00", "09:30~17:00", "09:30~17:00", "-"], "course": ["\uc0ac\uc0c1\uccb4\uc9c8\uacfc", "\uce68\uad6c\uacfc", "\ud55c\ubc29\ub0b4\uacfc", "\ud55c\ubc29\ubd80\uc778\uacfc", "\ud55c\ubc29\uc18c\uc544\uacfc", "\ud55c\ubc29\uc2e0\uacbd\uc815\uc2e0\uacfc", "\ud55c\ubc29\uc548\uc774\ube44\uc778\ud6c4\ud53c\ubd80\uacfc", "\ud55c\ubc29\uc7ac\ud65c\uc758\ud559\uacfc"]}, {"name": "\ud55c\ucd08\ud55c\uc758\uc6d0", "lat": "37.57902042698503", "lng": "127.04058319262234", "url": "/info/%ED%95%9C%EC%B4%88%ED%95%9C%EC%9D%98%EC%9B%90-%EC%84%9C%EC%9A%B8%ED%8A%B9%EB%B3%84%EC%8B%9C-%EB%8F%99%EB%8C%80%EB%AC%B8%EA%B5%AC-%EC%A0%9C%EA%B8%B0%EB%8F%99/", "workingTime": ["-", "09:00~18:00", "09:00~18:00", "09:00~18:00", "09:00~18:00", "09:00~18:00", "09:00~16:00", "-"], "course": ["\ud55c\ubc29\ub0b4\uacfc"]}, {"name": "\uacbd\ub3d9\ud55c\uc758\uc6d0", "lat": "17.662355555555557", "lng": "8.450911111111111", "url": "/info/%EA%B2%BD%EB%8F%99%ED%95%9C%EC%9D%98%EC%9B%90-%EC%84%9C%EC%9A%B8%ED%8A%B9%EB%B3%84%EC%8B%9C-%EB%8F%99%EB%8C%80%EB%AC%B8%EA%B5%AC-%EC%A0%9C%EA%B8%B0%EB%8F%99/", "workingTime": ["-", "10:00~18:00", "10:00~18:00", "10:00~18:00", "10:00~18:00", "10:00~18:00", "10:00~13:00", "-"], "course": ["\uc0ac\uc0c1\uccb4\uc9c8\uacfc", "\uce68\uad6c\uacfc", "\ud55c\ubc29\ub0b4\uacfc", "\ud55c\ubc29\ubd80\uc778\uacfc", "\ud55c\ubc29\uc18c\uc544\uacfc", "\ud55c\ubc29\uc2e0\uacbd\uc815\uc2e0\uacfc", "\ud55c\ubc29\uc548\uc774\ube44\uc778\ud6c4\ud53c\ubd80\uacfc", "\ud55c\ubc29\uc7ac\ud65c\uc758\ud559\uacfc"]}, {"name": "\ubb38\uacbd\ub2f9\ud55c\uc758\uc6d0", "lat": "37.5794361277585", "lng": "127.03678863071838", "url": "/info/%EB%AC%B8%EA%B2%BD%EB%8B%B9%ED%95%9C%EC%9D%98%EC%9B%90-%EC%84%9C%EC%9A%B8%ED%8A%B9%EB%B3%84%EC%8B%9C-%EB%8F%99%EB%8C%80%EB%AC%B8%EA%B5%AC-%EC%A0%9C%EA%B8%B0%EB%8F%99/", "workingTime": ["2,4\uc9f8\uc8fc10:00~15:00", "10:00~18:00", "10:00~18:00", "10:00~18:00", "10:00~18:00", "10:00~18:00", "10:00~15:00", "10:00~15:00"], "course": ["\uc0ac\uc0c1\uccb4\uc9c8\uacfc", "\uce68\uad6c\uacfc", "\ud55c\ubc29\ub0b4\uacfc", "\ud55c\ubc29\ubd80\uc778\uacfc", "\ud55c\ubc29\uc18c\uc544\uacfc", "\ud55c\ubc29\uc2e0\uacbd\uc815\uc2e0\uacfc", "\ud55c\ubc29\uc548\uc774\ube44\uc778\ud6c4\ud53c\ubd80\uacfc", "\ud55c\ubc29\uc7ac\ud65c\uc758\ud559\uacfc"]}, {"name": "\uace0\ub824\ud55c\uc758\uc6d0", "lat": "37.58594609817463", "lng": "127.03274761261962", "url": "/info/%EA%B3%A0%EB%A0%A4%ED%95%9C%EC%9D%98%EC%9B%90-%EC%84%9C%EC%9A%B8%ED%8A%B9%EB%B3%84%EC%8B%9C-%EB%8F%99%EB%8C%80%EB%AC%B8%EA%B5%AC-%EC%A0%9C%EA%B8%B0%EB%8F%99/", "workingTime": ["-", "09:30~18:00", "09:30~18:00", "09:30~18:00", "09:30~18:00", "09:30~18:00", "09:30~15:00", "-"], "course": ["\uc0ac\uc0c1\uccb4\uc9c8\uacfc", "\uce68\uad6c\uacfc", "\ud55c\ubc29\ub0b4\uacfc", "\ud55c\ubc29\ubd80\uc778\uacfc", "\ud55c\ubc29\uc18c\uc544\uacfc", "\ud55c\ubc29\uc2e0\uacbd\uc815\uc2e0\uacfc", "\ud55c\ubc29\uc548\uc774\ube44\uc778\ud6c4\ud53c\ubd80\uacfc", "\ud55c\ubc29\uc7ac\ud65c\uc758\ud559\uacfc"]}, {"name": "\ubaa9\ud654\ud55c\uc758\uc6d0", "lat": "37.580012761733556", "lng": "127.03680700742056", "url": "/info/%EB%AA%A9%ED%99%94%ED%95%9C%EC%9D%98%EC%9B%90-%EC%84%9C%EC%9A%B8%ED%8A%B9%EB%B3%84%EC%8B%9C-%EB%8F%99%EB%8C%80%EB%AC%B8%EA%B5%AC-%EC%A0%9C%EA%B8%B0%EB%8F%99/", "workingTime": ["-", "10:30~18:30", "10:30~18:30", "14:00~18:30", "10:30~18:30", "10:30~18:30", "10:30~16:00", "-"], "course": ["\uc0ac\uc0c1\uccb4\uc9c8\uacfc", "\uce68\uad6c\uacfc", "\ud55c\ubc29\ub0b4\uacfc", "\ud55c\ubc29\ubd80\uc778\uacfc", "\ud55c\ubc29\uc18c\uc544\uacfc", "\ud55c\ubc29\uc2e0\uacbd\uc815\uc2e0\uacfc", "\ud55c\ubc29\uc548\uc774\ube44\uc778\ud6c4\ud53c\ubd80\uacfc", "\ud55c\ubc29\uc7ac\ud65c\uc758\ud559\uacfc"]}, {"name": "\ubc31\ubd09\ud55c\uc758\uc6d0", "lat": "37.578906072097276", "lng": "127.03764875718176", "url": "/info/%EB%B0%B1%EB%B4%89%ED%95%9C%EC%9D%98%EC%9B%90-%EC%84%9C%EC%9A%B8%ED%8A%B9%EB%B3%84%EC%8B%9C-%EB%8F%99%EB%8C%80%EB%AC%B8%EA%B5%AC-%EC%A0%9C%EA%B8%B0%EB%8F%99/", "workingTime": ["2,4\uc9f8\uc8fc10:00~15:00", "10:00~18:00", "10:00~18:00", "10:00~18:00", "10:00~18:00", "10:00~18:00", "10:00~18:00", "-"], "course": ["\ud55c\ubc29\ub0b4\uacfc"]}, {"name": "\ub3d9\uc591\ud5c8\ube0c\ud55c\uc758\uc6d0", "lat": "37.5809855605", "lng": "127.0376769545", "url": "/info/%EB%8F%99%EC%96%91%ED%97%88%EB%B8%8C%ED%95%9C%EC%9D%98%EC%9B%90-%EC%84%9C%EC%9A%B8%ED%8A%B9%EB%B3%84%EC%8B%9C-%EB%8F%99%EB%8C%80%EB%AC%B8%EA%B5%AC-%EC%A0%9C%EA%B8%B0%EB%8F%99/", "workingTime": ["-", "09:00~18:00", "09:00~18:00", "09:00~18:00", "09:00~18:00", "09:00~18:00", "09:00~17:00", "-"], "course": ["\uc0ac\uc0c1\uccb4\uc9c8\uacfc", "\uce68\uad6c\uacfc", "\ud55c\ubc29\ub0b4\uacfc", "\ud55c\ubc29\ubd80\uc778\uacfc", "\ud55c\ubc29\uc18c\uc544\uacfc", "\ud55c\ubc29\uc2e0\uacbd\uc815\uc2e0\uacfc", "\ud55c\ubc29\uc548\uc774\ube44\uc778\ud6c4\ud53c\ubd80\uacfc", "\ud55c\ubc29\uc7ac\ud65c\uc758\ud559\uacfc"]}, {"name": "\ucd5c\ud601\ud55c\uc758\uc6d0", "lat": "37.5806070446", "lng": "127.0379846988", "url": "/info/%EC%B5%9C%ED%98%81%ED%95%9C%EC%9D%98%EC%9B%90-%EC%84%9C%EC%9A%B8%ED%8A%B9%EB%B3%84%EC%8B%9C-%EB%8F%99%EB%8C%80%EB%AC%B8%EA%B5%AC-%EC%A0%9C%EA%B8%B0%EB%8F%99/", "workingTime": ["-", "09:30~18:30", "09:30~18:30", "09:30~19:30", "-", "09:30~18:30", "09:30~16:30", "-"], "course": ["\uc0ac\uc0c1\uccb4\uc9c8\uacfc", "\uce68\uad6c\uacfc", "\ud55c\ubc29\ub0b4\uacfc", "\ud55c\ubc29\ubd80\uc778\uacfc", "\ud55c\ubc29\uc18c\uc544\uacfc", "\ud55c\ubc29\uc2e0\uacbd\uc815\uc2e0\uacfc", "\ud55c\ubc29\uc548\uc774\ube44\uc778\ud6c4\ud53c\ubd80\uacfc", "\ud55c\ubc29\uc7ac\ud65c\uc758\ud559\uacfc"]}, {"name": "\ubbf8\uba85\uc131\ud55c\uc758\uc6d0", "lat": "37.5786792059", "lng": "127.0370780514", "url": "/info/%EB%AF%B8%EB%AA%85%EC%84%B1%ED%95%9C%EC%9D%98%EC%9B%90-%EC%84%9C%EC%9A%B8%ED%8A%B9%EB%B3%84%EC%8B%9C-%EB%8F%99%EB%8C%80%EB%AC%B8%EA%B5%AC-%EC%A0%9C%EA%B8%B0%EB%8F%99/", "workingTime": ["-", "10:00~17:00", "10:00~17:00", "10:00~17:00", "10:00~17:00", "10:00~17:00", "10:00~13:00", "-"], "course": ["\uc0ac\uc0c1\uccb4\uc9c8\uacfc", "\uce68\uad6c\uacfc", "\ud55c\ubc29\ub0b4\uacfc", "\ud55c\ubc29\ubd80\uc778\uacfc", "\ud55c\ubc29\uc18c\uc544\uacfc", "\ud55c\ubc29\uc2e0\uacbd\uc815\uc2e0\uacfc", "\ud55c\ubc29\uc548\uc774\ube44\uc778\ud6c4\ud53c\ubd80\uacfc", "\ud55c\ubc29\uc7ac\ud65c\uc758\ud559\uacfc"]}, {"name": "\uba85\ubb38\ud55c\uc758\uc6d0", "lat": "37.5815295654", "lng": "127.0382840493", "url": "/info/%EB%AA%85%EB%AC%B8%ED%95%9C%EC%9D%98%EC%9B%90-%EC%84%9C%EC%9A%B8%ED%8A%B9%EB%B3%84%EC%8B%9C-%EB%8F%99%EB%8C%80%EB%AC%B8%EA%B5%AC-%EC%A0%9C%EA%B8%B0%EB%8F%99/", "workingTime": ["-", "10:30~18:30", "10:30~18:30", "10:30~18:30", "10:30~18:30", "10:30~18:30", "10:30~18:30", "-"], "course": ["\uce68\uad6c\uacfc", "\ud55c\ubc29\ub0b4\uacfc", "\ud55c\ubc29\ubd80\uc778\uacfc", "\ud55c\ubc29\uc18c\uc544\uacfc", "\ud55c\ubc29\uc2e0\uacbd\uc815\uc2e0\uacfc", "\ud55c\ubc29\uc548\uc774\ube44\uc778\ud6c4\ud53c\ubd80\uacfc", "\ud55c\ubc29\uc7ac\ud65c\uc758\ud559\uacfc"]}, {"name": "\uc601\ud654\ub2f9\ud55c\uc758\uc6d0", "lat": "37.578653965854144", "lng": "127.03710522959567", "url": "/info/%EC%98%81%ED%99%94%EB%8B%B9%ED%95%9C%EC%9D%98%EC%9B%90-%EC%84%9C%EC%9A%B8%ED%8A%B9%EB%B3%84%EC%8B%9C-%EB%8F%99%EB%8C%80%EB%AC%B8%EA%B5%AC-%EC%A0%9C%EA%B8%B0%EB%8F%99/", "workingTime": ["-", "10:00~17:50", "10:00~17:50", "10:00~17:50", "10:00~17:50", "10:00~17:50", "10:00~17:50", "10:00~17:50"], "course": ["\uc0ac\uc0c1\uccb4\uc9c8\uacfc", "\uce68\uad6c\uacfc", "\ud55c\ubc29\ub0b4\uacfc", "\ud55c\ubc29\ubd80\uc778\uacfc", "\ud55c\ubc29\uc18c\uc544\uacfc", "\ud55c\ubc29\uc2e0\uacbd\uc815\uc2e0\uacfc", "\ud55c\ubc29\uc548\uc774\ube44\uc778\ud6c4\ud53c\ubd80\uacfc", "\ud55c\ubc29\uc7ac\ud65c\uc758\ud559\uacfc"]}, {"name": "\uc591\uc81c\ud55c\uc758\uc6d0", "lat": "37.5787053948401", "lng": "127.03812842986751", "url": "/info/%EC%96%91%EC%A0%9C%ED%95%9C%EC%9D%98%EC%9B%90-%EC%84%9C%EC%9A%B8%ED%8A%B9%EB%B3%84%EC%8B%9C-%EB%8F%99%EB%8C%80%EB%AC%B8%EA%B5%AC-%EC%A0%9C%EA%B8%B0%EB%8F%99/", "workingTime": ["1,2,3,4,5\uc9f8\uc8fc10:30~17:30", "10:00~18:00", "10:00~18:00", "10:00~18:00", "10:00~18:00", "-", "10:30~17:30", "10:30~17:30"], "course": ["\uc0ac\uc0c1\uccb4\uc9c8\uacfc", "\uce68\uad6c\uacfc", "\ud55c\ubc29\ub0b4\uacfc", "\ud55c\ubc29\ubd80\uc778\uacfc", "\ud55c\ubc29\uc18c\uc544\uacfc", "\ud55c\ubc29\uc2e0\uacbd\uc815\uc2e0\uacfc", "\ud55c\ubc29\uc548\uc774\ube44\uc778\ud6c4\ud53c\ubd80\uacfc", "\ud55c\ubc29\uc7ac\ud65c\uc758\ud559\uacfc"]}, {"name": "\uc778\uc0dd\ud55c\uc758\uc6d0", "lat": "37.57954394682422", "lng": "127.03773964621978", "url": "/info/%EC%9D%B8%EC%83%9D%ED%95%9C%EC%9D%98%EC%9B%90-%EC%84%9C%EC%9A%B8%ED%8A%B9%EB%B3%84%EC%8B%9C-%EB%8F%99%EB%8C%80%EB%AC%B8%EA%B5%AC-%EC%A0%9C%EA%B8%B0%EB%8F%99/", "workingTime": ["1,2,3,4,5\uc9f8\uc8fc09:00~18:00", "09:00~18:00", "09:00~18:00", "09:00~18:00", "09:00~18:00", "09:00~18:00", "09:00~18:00", "09:00~18:00"], "course": ["\ud55c\ubc29\ub0b4\uacfc"]}, {"name": "\uae40\uc815\uc5f4\ud55c\uc758\uc6d0", "lat": "37.5807115598", "lng": "127.0379847519", "url": "/info/%EA%B9%80%EC%A0%95%EC%97%B4%ED%95%9C%EC%9D%98%EC%9B%90-%EC%84%9C%EC%9A%B8%ED%8A%B9%EB%B3%84%EC%8B%9C-%EB%8F%99%EB%8C%80%EB%AC%B8%EA%B5%AC-%EC%A0%9C%EA%B8%B0%EB%8F%99/", "workingTime": ["-", "09:00~18:00", "09:00~18:00", "-", "09:00~18:00", "09:00~18:00", "09:00~16:00", "09:00~16:00"], "course": ["\uc0ac\uc0c1\uccb4\uc9c8\uacfc", "\uce68\uad6c\uacfc", "\ud55c\ubc29\ub0b4\uacfc", "\ud55c\ubc29\ubd80\uc778\uacfc", "\ud55c\ubc29\uc18c\uc544\uacfc", "\ud55c\ubc29\uc2e0\uacbd\uc815\uc2e0\uacfc", "\ud55c\ubc29\uc548\uc774\ube44\uc778\ud6c4\ud53c\ubd80\uacfc", "\ud55c\ubc29\uc7ac\ud65c\uc758\ud559\uacfc"]}, {"name": "\uacbd\ud76c\ub2f9\ud55c\uc758\uc6d0", "lat": "37.57953435848447", "lng": "127.03794770149727", "url": "/info/%EA%B2%BD%ED%9D%AC%EB%8B%B9%ED%95%9C%EC%9D%98%EC%9B%90-%EC%84%9C%EC%9A%B8%ED%8A%B9%EB%B3%84%EC%8B%9C-%EB%8F%99%EB%8C%80%EB%AC%B8%EA%B5%AC-%EC%A0%9C%EA%B8%B0%EB%8F%99/", "workingTime": ["1,2,3,4,5\uc9f8\uc8fc09:00~18:00", "09:00~18:00", "09:00~18:00", "09:00~18:00", "09:00~18:00", "09:00~18:00", "09:00~18:00", "09:00~18:00"], "course": ["\uc0ac\uc0c1\uccb4\uc9c8\uacfc", "\uce68\uad6c\uacfc", "\ud55c\ubc29\ub0b4\uacfc", "\ud55c\ubc29\ubd80\uc778\uacfc", "\ud55c\ubc29\uc18c\uc544\uacfc", "\ud55c\ubc29\uc2e0\uacbd\uc815\uc2e0\uacfc", "\ud55c\ubc29\uc548\uc774\ube44\uc778\ud6c4\ud53c\ubd80\uacfc", "\ud55c\ubc29\uc7ac\ud65c\uc758\ud559\uacfc"]}, {"name": "\uc6d0\ub0a8\ud55c\uc758\uc6d0", "lat": "37.57866107309525", "lng": "127.0374357811813", "url": "/info/%EC%9B%90%EB%82%A8%ED%95%9C%EC%9D%98%EC%9B%90-%EC%84%9C%EC%9A%B8%ED%8A%B9%EB%B3%84%EC%8B%9C-%EB%8F%99%EB%8C%80%EB%AC%B8%EA%B5%AC-%EC%A0%9C%EA%B8%B0%EB%8F%99/", "workingTime": ["-", "10:00~17:30", "10:00~17:30", "10:00~17:30", "10:00~17:30", "10:00~17:30", "10:00~17:30", "10:00~17:30"], "course": [""]}, {"name": "\uc120\uad50\ud55c\uc758\uc6d0", "lat": "37.57946181771969", "lng": "127.03941485188261", "url": "/info/%EC%84%A0%EA%B5%90%ED%95%9C%EC%9D%98%EC%9B%90-%EC%84%9C%EC%9A%B8%ED%8A%B9%EB%B3%84%EC%8B%9C-%EB%8F%99%EB%8C%80%EB%AC%B8%EA%B5%AC-%EC%A0%9C%EA%B8%B0%EB%8F%99/", "workingTime": ["-", "10:00~18:00", "10:00~18:00", "10:00~18:00", "10:00~18:00", "10:00~18:00", "10:00~15:00", "10:00~15:00"], "course": ["\uc0ac\uc0c1\uccb4\uc9c8\uacfc", "\uce68\uad6c\uacfc", "\ud55c\ubc29\ub0b4\uacfc", "\ud55c\ubc29\ubd80\uc778\uacfc", "\ud55c\ubc29\uc18c\uc544\uacfc", "\ud55c\ubc29\uc2e0\uacbd\uc815\uc2e0\uacfc", "\ud55c\ubc29\uc548\uc774\ube44\uc778\ud6c4\ud53c\ubd80\uacfc", "\ud55c\ubc29\uc7ac\ud65c\uc758\ud559\uacfc"]}, {"name": "\uc2e0\ud604\ub300\ud55c\uc758\uc6d0", "lat": "37.57844492813644", "lng": "127.0371277674931", "url": "/info/%EC%8B%A0%ED%98%84%EB%8C%80%ED%95%9C%EC%9D%98%EC%9B%90-%EC%84%9C%EC%9A%B8%ED%8A%B9%EB%B3%84%EC%8B%9C-%EB%8F%99%EB%8C%80%EB%AC%B8%EA%B5%AC-%EC%A0%9C%EA%B8%B0%EB%8F%99/", "workingTime": ["-", "10:00~18:00", "10:00~18:00", "10:00~18:00", "10:00~18:00", "10:00~18:00", "10:00~18:00", "10:00~18:00"], "course": ["\uc0ac\uc0c1\uccb4\uc9c8\uacfc", "\uce68\uad6c\uacfc", "\ud55c\ubc29\ub0b4\uacfc", "\ud55c\ubc29\ubd80\uc778\uacfc", "\ud55c\ubc29\uc18c\uc544\uacfc", "\ud55c\ubc29\uc2e0\uacbd\uc815\uc2e0\uacfc", "\ud55c\ubc29\uc548\uc774\ube44\uc778\ud6c4\ud53c\ubd80\uacfc", "\ud55c\ubc29\uc7ac\ud65c\uc758\ud559\uacfc"]}, {"name": "\uae08\uac15\ud55c\uc758\uc6d0", "lat": "37.5786507269846", "lng": "127.0359368959449", "url": "/info/%EA%B8%88%EA%B0%95%ED%95%9C%EC%9D%98%EC%9B%90-%EC%84%9C%EC%9A%B8%ED%8A%B9%EB%B3%84%EC%8B%9C-%EB%8F%99%EB%8C%80%EB%AC%B8%EA%B5%AC-%EC%A0%9C%EA%B8%B0%EB%8F%99/", "workingTime": ["2,4\uc9f8\uc8fc10:00~16:00", "10:00~18:00", "10:00~18:00", "10:00~18:00", "10:00~18:00", "10:00~18:00", "10:00~16:00", "10:00~16:00"], "course": ["\uc0ac\uc0c1\uccb4\uc9c8\uacfc", "\uce68\uad6c\uacfc", "\ud55c\ubc29\ub0b4\uacfc", "\ud55c\ubc29\ubd80\uc778\uacfc", "\ud55c\ubc29\uc18c\uc544\uacfc", "\ud55c\ubc29\uc2e0\uacbd\uc815\uc2e0\uacfc", "\ud55c\ubc29\uc548\uc774\ube44\uc778\ud6c4\ud53c\ubd80\uacfc", "\ud55c\ubc29\uc7ac\ud65c\uc758\ud559\uacfc"]}, {"name": "\uc0c1\ub85d\ud55c\uc758\uc6d0", "lat": "37.578624837889826", "lng": "127.03804708852898", "url": "/info/%EC%83%81%EB%A1%9D%ED%95%9C%EC%9D%98%EC%9B%90-%EC%84%9C%EC%9A%B8%ED%8A%B9%EB%B3%84%EC%8B%9C-%EB%8F%99%EB%8C%80%EB%AC%B8%EA%B5%AC-%EC%A0%9C%EA%B8%B0%EB%8F%99/", "workingTime": ["-", "10:00~17:30", "10:00~17:30", "10:00~17:30", "10:00~17:30", "10:00~17:30", "10:00~17:30", "-"], "course": ["\uc0ac\uc0c1\uccb4\uc9c8\uacfc", "\uce68\uad6c\uacfc", "\ud55c\ubc29\ub0b4\uacfc", "\ud55c\ubc29\ubd80\uc778\uacfc", "\ud55c\ubc29\uc18c\uc544\uacfc", "\ud55c\ubc29\uc2e0\uacbd\uc815\uc2e0\uacfc", "\ud55c\ubc29\uc548\uc774\ube44\uc778\ud6c4\ud53c\ubd80\uacfc", "\ud55c\ubc29\uc7ac\ud65c\uc758\ud559\uacfc"]}, {"name": "\ud6a8\uc131\ud55c\uc758\uc6d0", "lat": "37.57883793480626", "lng": "127.03658453995352", "url": "/info/%ED%9A%A8%EC%84%B1%ED%95%9C%EC%9D%98%EC%9B%90-%EC%84%9C%EC%9A%B8%ED%8A%B9%EB%B3%84%EC%8B%9C-%EB%8F%99%EB%8C%80%EB%AC%B8%EA%B5%AC-%EC%A0%9C%EA%B8%B0%EB%8F%99/", "workingTime": ["1,2,3,4,5\uc9f8\uc8fc10:00~18:00", "10:00~18:00", "10:00~18:00", "10:00~18:00", "10:00~18:00", "-", "10:00~18:00", "10:00~18:00"], "course": ["\uc0ac\uc0c1\uccb4\uc9c8\uacfc", "\uce68\uad6c\uacfc", "\ud55c\ubc29\ub0b4\uacfc", "\ud55c\ubc29\ubd80\uc778\uacfc", "\ud55c\ubc29\uc18c\uc544\uacfc", "\ud55c\ubc29\uc2e0\uacbd\uc815\uc2e0\uacfc", "\ud55c\ubc29\uc548\uc774\ube44\uc778\ud6c4\ud53c\ubd80\uacfc", "\ud55c\ubc29\uc7ac\ud65c\uc758\ud559\uacfc"]}, {"name": "\uc6d0\ucc3d\ud55c\uc758\uc6d0", "lat": "37.579627047100004", "lng": "127.03709210659998", "url": "/info/%EC%9B%90%EC%B0%BD%ED%95%9C%EC%9D%98%EC%9B%90-%EC%84%9C%EC%9A%B8%ED%8A%B9%EB%B3%84%EC%8B%9C-%EB%8F%99%EB%8C%80%EB%AC%B8%EA%B5%AC-%EC%A0%9C%EA%B8%B0%EB%8F%99/", "workingTime": ["2,4\uc9f8\uc8fc11:00~15:00", "10:00~17:00", "10:00~17:00", "10:00~17:00", "10:00~17:00", "10:00~17:00", "10:00~16:00", "-"], "course": ["\uc0ac\uc0c1\uccb4\uc9c8\uacfc", "\uce68\uad6c\uacfc", "\ud55c\ubc29\ub0b4\uacfc", "\ud55c\ubc29\ubd80\uc778\uacfc", "\ud55c\ubc29\uc18c\uc544\uacfc", "\ud55c\ubc29\uc2e0\uacbd\uc815\uc2e0\uacfc", "\ud55c\ubc29\uc548\uc774\ube44\uc778\ud6c4\ud53c\ubd80\uacfc", "\ud55c\ubc29\uc7ac\ud65c\uc758\ud559\uacfc"]}, {"name": "\ubcf4\ud654\ub2f9\ud55c\uc758\uc6d0", "lat": "37.58191518761755", "lng": "127.03829330387289", "url": "/info/%EB%B3%B4%ED%99%94%EB%8B%B9%ED%95%9C%EC%9D%98%EC%9B%90-%EC%84%9C%EC%9A%B8%ED%8A%B9%EB%B3%84%EC%8B%9C-%EB%8F%99%EB%8C%80%EB%AC%B8%EA%B5%AC-%EC%A0%9C%EA%B8%B0%EB%8F%99/", "workingTime": ["-", "09:00~18:00", "09:00~18:00", "09:00~18:00", "09:00~18:00", "09:00~18:00", "09:00~15:00", "-"], "course": ["\uc0ac\uc0c1\uccb4\uc9c8\uacfc", "\uce68\uad6c\uacfc", "\ud55c\ubc29\ub0b4\uacfc", "\ud55c\ubc29\ubd80\uc778\uacfc", "\ud55c\ubc29\uc18c\uc544\uacfc", "\ud55c\ubc29\uc2e0\uacbd\uc815\uc2e0\uacfc", "\ud55c\ubc29\uc548\uc774\ube44\uc778\ud6c4\ud53c\ubd80\uacfc", "\ud55c\ubc29\uc7ac\ud65c\uc758\ud559\uacfc"]}, {"name": "\uc6d0\ubc31\uc81c\ub2f9\ud55c\uc758\uc6d0", "lat": "37.5815225295", "lng": "127.0377496813", "url": "/info/%EC%9B%90%EB%B0%B1%EC%A0%9C%EB%8B%B9%ED%95%9C%EC%9D%98%EC%9B%90-%EC%84%9C%EC%9A%B8%ED%8A%B9%EB%B3%84%EC%8B%9C-%EB%8F%99%EB%8C%80%EB%AC%B8%EA%B5%AC-%EC%A0%9C%EA%B8%B0%EB%8F%99/", "workingTime": ["-", "10:00~18:00", "10:00~18:00", "10:00~18:00", "10:00~18:00", "10:00~18:00", "10:00~13:00", "-"], "course": ["\ud55c\ubc29\ub0b4\uacfc"]}, {"name": "\ub300\uc9c0\ud55c\uc758\uc6d0", "lat": "37.5794790048", "lng": "127.0379705406", "url": "/info/%EB%8C%80%EC%A7%80%ED%95%9C%EC%9D%98%EC%9B%90-%EC%84%9C%EC%9A%B8%ED%8A%B9%EB%B3%84%EC%8B%9C-%EB%8F%99%EB%8C%80%EB%AC%B8%EA%B5%AC-%EC%A0%9C%EA%B8%B0%EB%8F%99/", "workingTime": ["2,4,5\uc9f8\uc8fc10:00~18:00", "10:00~18:00", "10:00~18:00", "10:00~18:00", "10:00~18:00", "10:00~18:00", "10:00~18:00", "-"], "course": ["\uc0ac\uc0c1\uccb4\uc9c8\uacfc", "\uce68\uad6c\uacfc", "\ud55c\ubc29\ub0b4\uacfc", "\ud55c\ubc29\ubd80\uc778\uacfc", "\ud55c\ubc29\uc18c\uc544\uacfc", "\ud55c\ubc29\uc2e0\uacbd\uc815\uc2e0\uacfc", "\ud55c\ubc29\uc548\uc774\ube44\uc778\ud6c4\ud53c\ubd80\uacfc", "\ud55c\ubc29\uc7ac\ud65c\uc758\ud559\uacfc"]}, {"name": "\ubd88\uc554\ud55c\uc758\uc6d0", "lat": "37.57976726003692", "lng": "127.03816540841137", "url": "/info/%EB%B6%88%EC%95%94%ED%95%9C%EC%9D%98%EC%9B%90-%EC%84%9C%EC%9A%B8%ED%8A%B9%EB%B3%84%EC%8B%9C-%EB%8F%99%EB%8C%80%EB%AC%B8%EA%B5%AC-%EC%A0%9C%EA%B8%B0%EB%8F%99/", "workingTime": ["-", "09:00~18:00", "09:00~18:00", "09:00~18:00", "09:00~18:00", "09:00~18:00", "09:00~18:00", "-"], "course": ["\uc0ac\uc0c1\uccb4\uc9c8\uacfc", "\uce68\uad6c\uacfc", "\ud55c\ubc29\ub0b4\uacfc", "\ud55c\ubc29\ubd80\uc778\uacfc", "\ud55c\ubc29\uc18c\uc544\uacfc", "\ud55c\ubc29\uc2e0\uacbd\uc815\uc2e0\uacfc", "\ud55c\ubc29\uc548\uc774\ube44\uc778\ud6c4\ud53c\ubd80\uacfc", "\ud55c\ubc29\uc7ac\ud65c\uc758\ud559\uacfc"]}, {"name": "\ubcf4\uac74\ub2f9\ud55c\uc758\uc6d0", "lat": "37.5788738461", "lng": "127.0369966376", "url": "/info/%EB%B3%B4%EA%B1%B4%EB%8B%B9%ED%95%9C%EC%9D%98%EC%9B%90-%EC%84%9C%EC%9A%B8%ED%8A%B9%EB%B3%84%EC%8B%9C-%EB%8F%99%EB%8C%80%EB%AC%B8%EA%B5%AC-%EC%A0%9C%EA%B8%B0%EB%8F%99/", "workingTime": ["3\uc9f8\uc8fc13:00~17:00", "10:00~18:00", "10:00~18:00", "10:00~18:00", "10:00~20:00", "10:00~18:00", "10:00~17:00", "-"], "course": ["\uc0ac\uc0c1\uccb4\uc9c8\uacfc", "\uce68\uad6c\uacfc", "\ud55c\ubc29\ub0b4\uacfc", "\ud55c\ubc29\ubd80\uc778\uacfc", "\ud55c\ubc29\uc18c\uc544\uacfc", "\ud55c\ubc29\uc2e0\uacbd\uc815\uc2e0\uacfc", "\ud55c\ubc29\uc548\uc774\ube44\uc778\ud6c4\ud53c\ubd80\uacfc", "\ud55c\ubc29\uc7ac\ud65c\uc758\ud559\uacfc"]}]