[{"name": "\uc758\ub8cc\ubc95\uc778\ubd80\uc5ec\uc758\ub8cc\uc7ac\ub2e8\ubd80\uc5ec\ub2e4\uc0ac\ub791\ubcd1\uc6d0", "lat": "36.228856055178426", "lng": "126.86978378718467", "url": "/info/%EC%9D%98%EB%A3%8C%EB%B2%95%EC%9D%B8%EB%B6%80%EC%97%AC%EC%9D%98%EB%A3%8C%EC%9E%AC%EB%8B%A8%EB%B6%80%EC%97%AC%EB%8B%A4%EC%82%AC%EB%9E%91%EB%B3%91%EC%9B%90-%EC%B6%A9%EC%B2%AD%EB%82%A8%EB%8F%84-%EB%B6%80%EC%97%AC%EA%B5%B0-%EC%9E%A5%EC%95%94%EB%A9%B4/", "workingTime": ["-", "08:30~17:30", "08:30~17:30", "08:30~17:30", "08:30~17:30", "08:30~17:30", "-", "-"], "course": ["\uacb0\ud575\uacfc", "\ub0b4\uacfc", "\uc18c\uc544\uccad\uc18c\ub144\uacfc", "\uc815\uc2e0\uac74\uac15\uc758\ud559\uacfc"]}, {"name": "\ubd80\uc5ec\uad70\uc7a5\uc554\uba74\ubcf4\uac74\uc9c0\uc18c", "lat": "36.24392343066684", "lng": "126.88676229739416", "url": "/info/%EB%B6%80%EC%97%AC%EA%B5%B0%EC%9E%A5%EC%95%94%EB%A9%B4%EB%B3%B4%EA%B1%B4%EC%A7%80%EC%86%8C-%EC%B6%A9%EC%B2%AD%EB%82%A8%EB%8F%84-%EB%B6%80%EC%97%AC%EA%B5%B0-%EC%9E%A5%EC%95%94%EB%A9%B4/", "workingTime": ["-", "09:00~18:00", "09:00~18:00", "09:00~18:00", "09:00~18:00", "09:00~18:00", "-", "-"], "course": ["\ub0b4\uacfc"]}, {"name": "\ubd80\uc5ec\uad70\uc7a5\uc554\uba74\uc9c0\ud1a0\ub9ac\ubcf4\uac74\uc9c4\ub8cc\uc18c", "lat": "36.21835067594648", "lng": "126.91272487707283", "url": "/info/%EB%B6%80%EC%97%AC%EA%B5%B0%EC%9E%A5%EC%95%94%EB%A9%B4%EC%A7%80%ED%86%A0%EB%A6%AC%EB%B3%B4%EA%B1%B4%EC%A7%84%EB%A3%8C%EC%86%8C-%EC%B6%A9%EC%B2%AD%EB%82%A8%EB%8F%84-%EB%B6%80%EC%97%AC%EA%B5%B0-%EC%9E%A5%EC%95%94%EB%A9%B4/", "workingTime": ["-", "09:00~18:00", "09:00~18:00", "09:00~18:00", "09:00~18:00", "09:00~18:00", "-", "-"], "course": [""]}]